wsiprocess/__init__.py
wsiprocess/annotation.py
wsiprocess/cli.py
wsiprocess/converter.py
wsiprocess/error.py
wsiprocess/patcher.py
wsiprocess/rule.py
wsiprocess/slide.py
wsiprocess/utils.py
wsiprocess/verify.py
wsiprocess/annotationparser/ASAP_parser.py
wsiprocess/annotationparser/GeoJson_parser.py
wsiprocess/annotationparser/NDPView_parser.py
wsiprocess/annotationparser/QuPath_parser.py
wsiprocess/annotationparser/SlideRunner_parser.py
wsiprocess/annotationparser/WSIDissector_parser.py
wsiprocess/annotationparser/__init__.py
wsiprocess/annotationparser/parser_utils.py
wsiprocess/converters/__init__.py
wsiprocess/converters/base_converter.py
wsiprocess/converters/wsiprocess_to_coco.py
wsiprocess/converters/wsiprocess_to_voc.py
wsiprocess/converters/wsiprocess_to_yolo.py
wsiprocess/pytorch/__init__.py
wsiprocess/pytorch/utils.py
wsiprocess/pytorch/wsidataloader.py
wsiprocess/pytorch/wsidataset.py
wsiprocess-1.1.1.data/scripts/cli.py
wsiprocess-1.1.1.dist-info/LICENSE
wsiprocess-1.1.1.dist-info/METADATA
wsiprocess-1.1.1.dist-info/WHEEL
wsiprocess-1.1.1.dist-info/entry_points.txt
wsiprocess-1.1.1.dist-info/top_level.txt
wsiprocess-1.1.1.dist-info/RECORD
