Metadata-Version: 2.1
Name: wsiprocess
Version: 1.1.1
Summary: Whole Slide Image (WSI) Processing Library
Home-page: https://github.com/tand826/wsiprocess
Author: Takumi Ando
Author-email: takumi.ando826@gmail.com
License: Apache License 2.0
Keywords: histopathology,cytopathology,medical-imaging,whole-slide-imaging,machine-learning
Platform: any
Classifier: Programming Language :: Python :: 3.6
Classifier: Programming Language :: Python :: 3.7
Classifier: Programming Language :: Python :: 3.8
Classifier: Programming Language :: Python :: 3.9
Classifier: Programming Language :: Python :: 3.10
Classifier: Operating System :: OS Independent
Requires-Python: >=3.6
License-File: LICENSE
Requires-Dist: lxml
Requires-Dist: numpy
Requires-Dist: opencv-python
Requires-Dist: openslide-python
Requires-Dist: pandas
Requires-Dist: psutil
Requires-Dist: tqdm
Provides-Extra: pyvips
Requires-Dist: pyvips ; extra == 'pyvips'
